mega/__init__.py
mega/crypto.py
mega/errors.py
mega/mega.py
mega.co.py-1.1.0.dist-info/LICENSE
mega.co.py-1.1.0.dist-info/METADATA
mega.co.py-1.1.0.dist-info/WHEEL
mega.co.py-1.1.0.dist-info/top_level.txt
mega.co.py-1.1.0.dist-info/RECORD
