Metadata-Version: 2.1
Name: mega.co.py
Version: 1.1.0
Summary: Python lib for the Mega.co.nz API
Home-page: https://github.com/staimerio/mega.py
Author: Braian Staimer
Author-email: braianflorian@gmail.com
License: Creative Commons Attribution-Noncommercial-Share Alike license
Requires-Dist: requests (>=0.10)
Requires-Dist: pycryptodome (<4.0.0,>=3.9.6)
Requires-Dist: pathlib (==1.0.1)
Requires-Dist: tenacity (<6.0.0,>=5.1.5)
